{
    "message": "Successfully retrieved categories",
    "result": true,
    "data": [
        { "categoryId": 1, "categoryName": "Fruits & Vegetables", "parentCategoryId": 0 },
        { "categoryId": 2, "categoryName": "Dairy & Bakery", "parentCategoryId": 0 },
        { "categoryId": 3, "categoryName": "Snacks & Beverages", "parentCategoryId": 0 },
        { "categoryId": 4, "categoryName": "Personal Care", "parentCategoryId": 0 },
        { "categoryId": 5, "categoryName": "Household Items", "parentCategoryId": 0 },
        { "categoryId": 6, "categoryName": "Electronics", "parentCategoryId": 0 },
        { "categoryId": 7, "categoryName": "Clothing & Apparel", "parentCategoryId": 0 },
        { "categoryId": 8, "categoryName": "Health & Wellness", "parentCategoryId": 0 },
        { "categoryId": 9, "categoryName": "Books & Stationery", "parentCategoryId": 0 },
        { "categoryId": 10, "categoryName": "Automotive", "parentCategoryId": 0 },
        { "categoryId": 11, "categoryName": "Office Supplies", "parentCategoryId": 0 },
        { "categoryId": 12, "categoryName": "Garden & Outdoor", "parentCategoryId": 0 },
        { "categoryId": 13, "categoryName": "Pet Supplies", "parentCategoryId": 0 },
        { "categoryId": 14, "categoryName": "Toys & Games", "parentCategoryId": 0 },
        { "categoryId": 15, "categoryName": "Music & Movies", "parentCategoryId": 0 },
        { "categoryId": 16, "categoryName": "Baby Products", "parentCategoryId": 0 },
        { "categoryId": 17, "categoryName": "Jewelry", "parentCategoryId": 0 },
        { "categoryId": 18, "categoryName": "Sports & Outdoors", "parentCategoryId": 0 },
        { "categoryId": 19, "categoryName": "Art & Crafts", "parentCategoryId": 0 },
        { "categoryId": 20, "categoryName": "Home Appliances", "parentCategoryId": 0 },
        { "categoryId": 21, "categoryName": "Furniture", "parentCategoryId": 0 },
        { "categoryId": 22, "categoryName": "Travel Accessories", "parentCategoryId": 0 },
        { "categoryId": 23, "categoryName": "Health & Personal Care", "parentCategoryId": 0 },
        { "categoryId": 24, "categoryName": "Computers & Accessories", "parentCategoryId": 0 },
        { "categoryId": 25, "categoryName": "Handmade Goods", "parentCategoryId": 0 },
        { "categoryId": 26, "categoryName": "Office Furniture", "parentCategoryId": 0 },
        { "categoryId": 27, "categoryName": "Safety & Security", "parentCategoryId": 0 },
        { "categoryId": 28, "categoryName": "Specialty Foods", "parentCategoryId": 0 },
        { "categoryId": 29, "categoryName": "Gifts", "parentCategoryId": 0 },
        { "categoryId": 30, "categoryName": "Seasonal Items", "parentCategoryId": 0 }
    ]
}
